{
    "swagger": "2.0",
    "info": {
        "contact": {}
    },
    "paths": {
        "/platform": {
            "post": {
                "description": "create platform",
                "consumes": [
                    "application/json"
                ],
                "produces": [
                    "application/json"
                ],
                "tags": [
                    "Platform"
                ],
                "summary": "create platform",
                "parameters": [
                    {
                        "description": "Request body",
                        "name": "request",
                        "in": "body",
                        "required": true,
                        "schema": {
                            "$ref": "#/definitions/application.CreateResourceRequest"
                        }
                    }
                ],
                "responses": {
                    "200": {
                        "description": "OK"
                    }
                }
            }
        }
    },
    "definitions": {
        "application.CreateResourceRequest": {
            "type": "object",
            "properties": {
                "name": {
                    "type": "string"
                },
                "property": {
                    "type": "object",
                    "additionalProperties": {
                        "type": "string"
                    }
                },
                "rest": {
                    "type": "string"
                },
                "url": {
                    "type": "string"
                }
            }
        }
    }
}